srcs/Controller.v
`timescale 1ns / 1ps
module washing_machine_ctrl
(
    input clk,
    input wire lid, coin, cancel,
    input wire [1:0] mode,
    output wire idle_op, ready_op, soak_op, wash_op, rinse_op, spin_op,
    output wire coin_rtn, water_inlet, 
    output reg soak_done, wash_done, rinse_done, spin_done
);

localparam[1:0]
    MODE1 = 0,
    MODE2 = 1,
    MODE3 = 2,
    NOSEL = 4;
        
reg [2:0] wash_Counter, rinse_Counter, spin_Counter, soak_Counter;

    parameter IDLE = 3'd0 ;
    parameter READY = 3'd1;
    parameter SOAK = 3'd2;
    parameter WASH = 3'd3;
    parameter RINSE = 3'd4;
    parameter SPIN = 3'd5;
    
    integer SOAK_TIME;
    integer WASH_TIME;
    integer RINSE_TIME;
    integer SPIN_TIME;
	
	/* mode1
       Soak  : 1 mins
       Wash  : 2 mins
       Rinse : 2 mins
       Spin  : 2 mins   
	   
	   mode2 
       Soak  : 2 mins
       Wash  : 3 mins
       Rinse : 3 mins
       Spin  : 3 mins   
	   
	   mode3 
       Soak  : 3 mins
       Wash  : 5 mins
       Rinse : 5 mins
       Spin  : 5 mins   */
    
// signal declaration
reg [2:0] r_reg = 0, r_next;
    
always @(posedge clk)
    begin
        r_reg = r_next;
    end

always @ (negedge clk) begin 
    if (r_reg == IDLE || r_reg == READY) begin
        wash_Counter = 0;
        rinse_Counter = 0;
        spin_Counter = 0;
        soak_Counter = 0;
        wash_done = 0;
        rinse_done = 0;
        spin_done = 0; 
        soak_done = 0;
    end 

    case (r_reg)    
        SOAK:        
            soak_Counter = soak_Counter + 1'd1;            
        WASH: 
            wash_Counter = wash_Counter + 1'd1;               
        RINSE: 
            rinse_Counter = rinse_Counter + 1'd1;         
        SPIN: 
            spin_Counter = spin_Counter + 1'd1;               
    endcase
end

// next-state logic + MODE logic
always @*
begin
    r_next <= r_reg;
    if (lid == 1 || cancel == 1)
        r_next  <= IDLE;
        
    case(r_reg)
    IDLE:   begin
        if(lid == 0 && coin == 1 && cancel == 0)
            r_next <= READY;
            case(mode)
                MODE1:  begin
                    SOAK_TIME = 1;
                    WASH_TIME = 2;
                    RINSE_TIME = 2;
                    SPIN_TIME = 2;
                  end
            
                MODE2: begin
                    SOAK_TIME = 2;
                    WASH_TIME = 3;
                    RINSE_TIME = 3;
                    SPIN_TIME = 3;
              end
            
                MODE3: begin
                    SOAK_TIME = 3;
                    WASH_TIME = 5;
                    RINSE_TIME = 5;
                    SPIN_TIME = 5;
              end
            endcase
          end
    
    READY:
        if (mode == 2'b00 || mode == 2'b01 || mode == 2'b10)
            if (lid == 0 && cancel == 0)
                r_next <= SOAK;

    SOAK:   begin
        if (soak_Counter == SOAK_TIME)
            soak_done <= 1;
        if (lid == 0 && cancel == 0)
            if(soak_done)
                r_next <= WASH;
      end
         
    WASH:   begin
        if (wash_Counter == WASH_TIME)
            wash_done <= 1;
        if (lid == 0 && cancel == 0)
            if(wash_done)
                r_next <= RINSE;
      end
            
    RINSE:  begin
        if (rinse_Counter == RINSE_TIME)
            rinse_done <= 1;
        if (lid == 0 && cancel == 0)
            if(rinse_done)
                r_next <= SPIN;
      end
      
    SPIN:   begin
        if (spin_Counter == SPIN_TIME)
            spin_done <= 1;   
        if (lid == 0 && cancel == 0)
            if(spin_done)
                r_next <= IDLE;       
      end
            
    default: r_next <= IDLE;
    
    endcase

end

//output logic
assign idle_op = (r_reg == IDLE);
assign ready_op = (r_reg ==READY);
assign soak_op = (r_reg == SOAK);
assign wash_op = (r_reg == WASH);
assign rinse_op = (r_reg == RINSE);
assign spin_op = (r_reg == SPIN);
assign coin_rtn = (r_reg == READY) && (cancel == 1);
assign water_inlet = (r_reg == SOAK) || (r_reg == RINSE);

endmodule

sim/testbench.v
`timescale 1ns / 1ps

module washing_machine_tb;
  // Inputs
  reg clk;
  reg lid;
  reg coin;
  reg cancel;
  reg [1:0] mode;
 
  
  // Outputs
  wire soak_done, wash_done, rinse_done, spin_done;
  wire idle_op, ready_op, soak_op, wash_op, rinse_op, spin_op;
  wire coin_rtn, water_inlet;
  
  // Instantiate the design under test (DUT)
  washing_machine_ctrl uut (
            .clk(clk),
            .lid(lid),
            .coin(coin),
            .cancel(cancel),
            .soak_done(soak_done),
            .wash_done(wash_done),
            .rinse_done(rinse_done),
            .spin_done(spin_done),
            .mode(mode),
            .idle_op(idle_op),
            .ready_op(ready_op),
            .soak_op(soak_op),
            .wash_op(wash_op),
            .rinse_op(rinse_op),
            .spin_op(spin_op),
            .coin_rtn(coin_rtn),
            .water_inlet(water_inlet)
  );

  // Clock generation
  initial begin
    clk = 0;
    forever #5 clk = ~clk;
  end

  initial begin
    // Initialize inputs
    lid = 1;
    coin = 0;
    cancel = 0;

    // Apply stimulus

    // You can add more stimulus here as needed

    #100 $finish; // Finish simulation after a while
  end
endmodule

sim/dump.vcd
$date
	Tue Dec 26 09:03:15 2023
$end
$version
	Icarus Verilog
$end
$timescale
	1ps
$end
$scope module washing_machine_tb $end
$var wire 1 ! water_inlet $end
$var wire 1 " wash_op $end
$var wire 1 # wash_done $end
$var wire 1 $ spin_op $end
$var wire 1 % spin_done $end
$var wire 1 & soak_op $end
$var wire 1 ' soak_done $end
$var wire 1 ( rinse_op $end
$var wire 1 ) rinse_done $end
$var wire 1 * ready_op $end
$var wire 1 + idle_op $end
$var wire 1 , coin_rtn $end
$var reg 1 - cancel $end
$var reg 1 . clk $end
$var reg 1 / coin $end
$var reg 1 0 lid $end
$var reg 2 1 mode [1:0] $end
$scope module uut $end
$var wire 1 - cancel $end
$var wire 1 . clk $end
$var wire 1 / coin $end
$var wire 1 , coin_rtn $end
$var wire 1 0 lid $end
$var wire 2 2 mode [1:0] $end
$var wire 1 ! water_inlet $end
$var wire 1 " wash_op $end
$var wire 1 $ spin_op $end
$var wire 1 & soak_op $end
$var wire 1 ( rinse_op $end
$var wire 1 * ready_op $end
$var wire 1 + idle_op $end
$var parameter 3 3 IDLE $end
$var parameter 2 4 MODE1 $end
$var parameter 2 5 MODE2 $end
$var parameter 2 6 MODE3 $end
$var parameter 2 7 NOSEL $end
$var parameter 3 8 READY $end
$var parameter 3 9 RINSE $end
$var parameter 3 : SOAK $end
$var parameter 3 ; SPIN $end
$var parameter 3 < WASH $end
$var reg 3 = r_next [2:0] $end
$var reg 3 > r_reg [2:0] $end
$var reg 3 ? rinse_Counter [2:0] $end
$var reg 1 ) rinse_done $end
$var reg 3 @ soak_Counter [2:0] $end
$var reg 1 ' soak_done $end
$var reg 3 A spin_Counter [2:0] $end
$var reg 1 % spin_done $end
$var reg 3 B wash_Counter [2:0] $end
$var reg 1 # wash_done $end
$var integer 32 C RINSE_TIME [31:0] $end
$var integer 32 D SOAK_TIME [31:0] $end
$var integer 32 E SPIN_TIME [31:0] $end
$var integer 32 F WASH_TIME [31:0] $end
$upscope $end
$upscope $end
$enddefinitions $end
$comment Show the parameter values. $end
$dumpall
b11 <
b101 ;
b10 :
b100 9
b1 8
b0 7
b10 6
b1 5
b0 4
b0 3
$end
#0
$dumpvars
bx F
bx E
bx D
bx C
b0 B
b0 A
b0 @
b0 ?
b0 >
b0 =
bx 2
bx 1
10
0/
0.
0-
0,
1+
0*
0)
0(
0'
0&
0%
0$
0#
0"
0!
$end
#5000
1.
#10000
b1 =
0.
b1 1
b1 2
1/
00
#15000
b10 =
b11 E
b11 C
b11 F
b10 D
0+
1*
b1 >
1.
#20000
0.
#25000
1!
0*
1&
b10 >
1.
#30000
b1 @
0.
#35000
1.
#40000
b11 =
1'
b10 @
0.
#45000
0!
0&
1"
b11 >
1.
#50000
b1 B
0.
#55000
1.
#60000
b10 B
0.
#65000
1.
#70000
b100 =
1#
b11 B
0.
#75000
1!
0"
1(
b100 >
1.
#80000
b1 ?
0.
#85000
1.
#90000
b10 ?
0.
#95000
1.
#100000
b101 =
1)
b11 ?
0.
#105000
0!
0(
1$
b101 >
1.
#110000
b1 A
0.
#115000
1.
#120000
b10 A
0.
#125000
1.
#130000
b0 =
1%
b11 A
0.
#135000
b1 =
1+
0$
b0 >
1.
#140000
0'
0%
0)
0#
b0 @
b0 A
b0 ?
b0 B
0.
#145000
b10 =
0+
1*
b1 >
1.
#150000
0.
#155000
1!
0*
1&
b10 >
1.
#160000
b1 @
0.
#165000
1.
#170000
b11 =
1'
b10 @
0.
#175000
0!
0&
1"
b11 >
1.
#180000
b1 B
0.
#185000
1.
#190000
b10 B
0.
